rvg/__init__.py
rvg/cli.py
rvg/numpyrvg/__init__.py
rvg/numpyrvg/numpyrvg.py
rvg/numpyrvg/utils.py
rvg-0.1.11.dist-info/LICENSE
rvg-0.1.11.dist-info/METADATA
rvg-0.1.11.dist-info/WHEEL
rvg-0.1.11.dist-info/entry_points.txt
rvg-0.1.11.dist-info/top_level.txt
rvg-0.1.11.dist-info/RECORD
