Metadata-Version: 2.1
Name: rvg
Version: 0.1.11
Summary: random values generator
Home-page: https://github.com/zehanort/rvg
Author: Sotiris Niarchos
Author-email: sot.niarchos@gmail.com
License: MIT
Download-URL: https://github.com/zehanort/rvg/releases
Platform: UNKNOWN
Classifier: Development Status :: 3 - Alpha
Classifier: Intended Audience :: Developers
Classifier: Intended Audience :: Other Audience
Classifier: Intended Audience :: Science/Research
Classifier: License :: OSI Approved :: MIT License
Classifier: Operating System :: OS Independent
Classifier: Natural Language :: English
Classifier: Programming Language :: Python
Classifier: Topic :: Software Development :: Libraries :: Python Modules
Classifier: Topic :: Utilities
Requires-Python: >=3.5
Requires-Dist: numpy
